mteb/__init__.py
mteb/cmd.py
mteb/logging.py
mteb/abstasks/AbsTask.py
mteb/abstasks/AbsTaskBitextMining.py
mteb/abstasks/AbsTaskClassification.py
mteb/abstasks/AbsTaskClustering.py
mteb/abstasks/AbsTaskPairClassification.py
mteb/abstasks/AbsTaskReranking.py
mteb/abstasks/AbsTaskRetrieval.py
mteb/abstasks/AbsTaskSTS.py
mteb/abstasks/AbsTaskSummarization.py
mteb/abstasks/CrosslingualTask.py
mteb/abstasks/LangMapping.py
mteb/abstasks/MultilingualTask.py
mteb/abstasks/TaskMetadata.py
mteb/abstasks/__init__.py
mteb/evaluation/MTEB.py
mteb/evaluation/__init__.py
mteb/evaluation/evaluators/BitextMiningEvaluator.py
mteb/evaluation/evaluators/ClassificationEvaluator.py
mteb/evaluation/evaluators/ClusteringEvaluator.py
mteb/evaluation/evaluators/Evaluator.py
mteb/evaluation/evaluators/PairClassificationEvaluator.py
mteb/evaluation/evaluators/RerankingEvaluator.py
mteb/evaluation/evaluators/RetrievalEvaluator.py
mteb/evaluation/evaluators/STSEvaluator.py
mteb/evaluation/evaluators/SummarizationEvaluator.py
mteb/evaluation/evaluators/__init__.py
mteb/evaluation/evaluators/utils.py
mteb/tasks/__init__.py
mteb/tasks/BitextMining/__init__.py
mteb/tasks/BitextMining/da/BornholmskBitextMining.py
mteb/tasks/BitextMining/da/__init__.py
mteb/tasks/BitextMining/multilingual/BUCCBitextMining.py
mteb/tasks/BitextMining/multilingual/DiaBLaBitextMining.py
mteb/tasks/BitextMining/multilingual/FloresBitextMining.py
mteb/tasks/BitextMining/multilingual/NorwegianCourtsBitextMining.py
mteb/tasks/BitextMining/multilingual/TatoebaBitextMining.py
mteb/tasks/BitextMining/multilingual/__init__.py
mteb/tasks/Classification/__init__.py
mteb/tasks/Classification/da/AngryTweetsClassification.py
mteb/tasks/Classification/da/DKHateClassification.py
mteb/tasks/Classification/da/DalajClassification.py
mteb/tasks/Classification/da/DanishPoliticalCommentsClassification.py
mteb/tasks/Classification/da/DdiscoCohesionClassification.py
mteb/tasks/Classification/da/LccSentimentClassification.py
mteb-2.0.0.dist-info/LICENSE
mteb-2.0.0.dist-info/METADATA
mteb-2.0.0.dist-info/WHEEL
mteb-2.0.0.dist-info/entry_points.txt
mteb-2.0.0.dist-info/top_level.txt
mteb-2.0.0.dist-info/RECORD
