Metadata-Version: 2.1
Name: mteb
Version: 2.0.0
Summary: Massive Text Embedding Benchmark
Author-email: MTEB Contributors <niklas@huggingface.co>, nouamane@huggingface.co, info@nils-reimers.de
License: Apache License
Project-URL: homepage, https://github.com/embeddings-benchmark/mteb
Project-URL: Huggingface Organization, https://huggingface.co/mteb
Project-URL: Source Code, https://github.com/embeddings-benchmark/mteb
Keywords: deep learning,text embeddings,benchmark
Classifier: Development Status :: 4 - Beta
Classifier: Environment :: Console
Classifier: Intended Audience :: Developers
Classifier: Intended Audience :: Information Technology
Classifier: License :: OSI Approved :: Apache Software License
Classifier: Operating System :: OS Independent
Classifier: Programming Language :: Python
Requires-Python: >=3.8
License-File: LICENSE
Requires-Dist: datasets >=2.2.0
Requires-Dist: jsonlines
Requires-Dist: numpy
Requires-Dist: requests >=2.26.0
Requires-Dist: scikit-learn >=1.0.2
Requires-Dist: scipy
Requires-Dist: sentence-transformers >=2.2.0
Requires-Dist: torch
Requires-Dist: tqdm
Requires-Dist: rich
Requires-Dist: pytrec-eval
Requires-Dist: pydantic
Requires-Dist: typing-extensions
Requires-Dist: eval-type-backport
Provides-Extra: dev
Requires-Dist: ruff >=0.0.254 ; extra == 'dev'
Requires-Dist: pytest ; extra == 'dev'
Requires-Dist: pytest-xdist ; extra == 'dev'
